[{"2000001":"Tu Caja Express CLT","3000001":"TU CAJA EXPRESS SC","4000001":"TU CAJA EXPRESS RDU","5000001":"Reservada","6000001":"Reservada","7000001":"Reservada","8000001":"Reservada","9000001":"Reservada","10000001":"Reservada","11000001":"Reservada","12000001":"Reservada","13000001":"Reservada","14000001":"Reservada","15000001":"TU CAJA EXPRESS CHARLESTON","16000001":"Reservada","17000001":"Reservada","18000001":"Tu Caja Express Wil","19000001":"Reservada","20000001":"Reservada","21000001":"RDU-EAST DOS MUNDOS","22000001":"CLT-LOC ELECKTRA AMERICA CHARLOTTE","23000001":"VA-CHES LA MISION SUPERMARKET","24000001":"CLT-WEST TIENDA MEXICO LLANCASTER","25000001":"CLT-LOC SERVICIOS UNIDOS POR AMERIC","26000001":"WS-NW TIENDA EL CENTRO","27000001":"RDU-SOU RIVERAS SUPER MARKET","28000001":"RDU-DUR VARIEDADES RLB","29000001":"RDU-DUR EL CHAPIN","30000001":"CLT-WEST SHELLY GROCERY","31000001":"Tu Caja Express Columbia SC","32000001":"WS-WEST TIENDA EL MANA","33000001":"VA-CHES LA MEXICANA MINI MARKET","34000001":"WS-WEST RINCON HISPANO","35000001":"COL - LOCAL RIVERAS SUPER MERCADO C","36000001":"WS-VIRG LA ESTRELLA","37000001":"WS-WEST EL EXPRESSO MEXICANO","38000001":"SC-LOCAL TIENDA GUATEMALA","39000001":"WIL-SOU TIENDA Y TORTILLERIA EL COC","40000001":"VA-RICH LATINOS UNIDOS","41000001":"WS-NOR LA RANCHERITA","42000001":"SC-LOCAL TIENDA EL PASO","43000001":"SC-WEST 2 LOS NENES BAKERY","44000001":"SC-WEST 2 EL TREBOL","45000001":"SC-EAST TIENDA MI VERACRUZ","46000001":"VA-CHES MI FAVORITA","47000001":"WS-NW LA ESTRELLA","48000001":"CLT-WEST REINA WHOLE SALERS","49000001":"WS-NOR CONEXION HISPANA","50000001":"RDU-LOC MI CASITA","51000001":"CLT-LOC PATRICIA CANALES","52000001":"RDU-DUR OLGA GOMEZ","53000001":"WS-WEST CHAPIN STORE","54000001":"WS-LOC- LA ESMERALDA","55000001":"CLT-ROCK ARACELI CALLEJA GONZALEZ C","56000001":"WIL-SOU SIN FRONTERAS","57000001":"CHAR-SAV 2 MIGUELITO","58000001":"CLT-LOC LA PROVIDECIA #2","59000001":"WS-WEST COUNTRY SQ FRESH CLT","60000001":"WIL-N WES SUPER MERCADO HISPANO","61000001":"VA-CHES LA KORITA","62000001":"KNOX-LOC ESPECIAL EXPRESS","63000001":"CLT-LOC LA CHIQUITITA","64000001":"VA-RICH PREMIER DOCUMENTS","65000001":"RDU-EAST W MB QUICK & SHOOPE","66000001":"WIL-NOR TIENDA GABY","67000001":"WIL-LOC LA CHIQUITA","68000001":"WIL-NOR TIENDA MARISOL","69000001":"CHATT - WEST GUATEMALA EL QUETZAL","70000001":"WS-WEST RINCONCITO HISPANO","71000001":"SC-LOCAL SUPERMERCADO EBENEZER","72000001":"WS-LOC TIENDA MEXICANA NATI","73000001":"RDU-LOC LATINOS EXPRESS","74000001":"SC-WEST 2 EL GIRASOL","75000001":"VA-CHES TIENDA MEXICANA PENIEL #2","76000001":"SC-WEST 1 EL MERCADITO SILVA","77000001":"CLT-LOC TIENDA MEXICANA MI CAFE","78000001":"CHATT - WEST LA TIENDITA","79000001":"SC-WEST 2 LA MICHOACANA NC-SC","80000001":"KNOX-NOR TIENDA DOÑA ROSA","81000001":"CHAR-SAV 2 LA SALSA GA","82000001":"CLT-WEST LA LUPITA GROCERY STOR","83000001":"CHAR-LOC D MODA IMPERIAL LLC","84000001":"CLT-LOC MI TIENDITA MINI MARKET / G","85000001":"WS-NOR LA SIERRA BURLINGTON","86000001":"KNOX-NOR TIENDA RAMOS","87000001":"WS-NW TIENDA MEX LAS FLORES","88000001":"VA-CHES LA PERLA","89000001":"RDU-EAST MERCADITO LA LUZ","90000001":"Tu Caja Express USA","91000001":"CHATT - WEST SUPERMERCADO EL REY","92000001":"CHATT-LOC TIENDA LATINA 2","93000001":"VA-CHES LA TIENDA GROCERY","94000001":"RDU-EAST ANA GABRIELA TORO","95000001":"CHAR-SAV 2 LA TAPATIA PRODUCTOS LAT","96000001":"KNOX-NOR MARTINEZ MEXICAN STORE","97000001":"WIL-SOUTH TIENDA EL MILAGRO","98000001":"WS-VIRG LA GUADALUPANA","99000001":"CLT-ROCK MI MORENITA","100000001":"SC-LOCAL SM LOS BAUTISTA","101000001":"RDU-EAST TIENDA EL LAGO","102000001":"COL - LOCAL TIENDA GUATEMALA","103000001":"WIL-LOC LA VAQUITA","104000001":"WIL-SOU LA OLANCHANA II","105000001":"COL - EAST TIENDA MEXICANA VERACRUZ","106000001":"WS-NW GROCERY STORE LA MICHOACANA","108000001":"SC-LOCAL TIENDA EL TIKAL","109000001":"CLT- LOC MONICA DEL CID NC","111000001":"RDU-SOU EL RINCON HISPANO","113000001":"WIL-LOC OVIDIO ROBLERO","114000001":"CLT-LOC CHARLOTTE MULTISERVICIOS","115000001":"WS-NOR GROCERY EL AZTECA","116000001":"WIL-N WES LA PLAZA CENTRAL","117000001":"SC-LOCAL EL PADRINO","118000001":"CLT-LOC SARYS TRAVEL","119000001":"VA-CHES LA PLAYA","120000001":"CHATT-EAST TIENDA LATINA","121000001":"CLT-WEST LA FAVORITA MINI MARKET","122000001":"NASH - SOUTH MI PUEBLITO MEXICAN MA","124000001":"WIL-SOU MARGARITA MENDEZ","125000001":"WS-LOC LA BODEGA LATINA","126000001":"WIL-LOC EL MERCADITO","127000001":"CHATT - WEST LA GUERRERENSE","128000001":"VA-CHES LUIS TUN (COLECTOR INDEPEND","129000001":"CLT-WEST PUPUSERIA MAMA MIA","130000001":"SC-LOCAL CHAVEZ MARKET","131000001":"JACK - LOC TIENDA Y RESTAURANTE 502","132000001":"WIL-N WES TIENDA GARIBALDY","133000001":"WIL-SOU TIENDA LA IDEAL","134000001":"SC-LOCAL Supermercado Su Hogar","135000001":"JACK - LOC TIENDA EL QUETZAL JACKSO","136000001":"COL - LOCAL RIVERAS GASTON","137000001":"CHAR-SAV 1 LAS MERCEDES GROCERY GA","138000001":"WS-LOC TIENDA CRYSTAL","139000001":"KNOX-LOC TIENDA HISPANA MARTINA","140000001":"KNOX-NOR TIENDA EL QUETZAL","141000001":"WIL-NOR TIENDA LA FE Y TORTILLERIA","142000001":"CHAR-LOC LA CANTERA SUPERMARKET","143000001":"CHATT - SOUTH TIENDA JISSEL","145000001":"RDU-SOU TACOS DON VARGAS SUPER MARK","147000001":"CLT-LOC ARTESANIA LOS POTRILLOS","148000001":"VA-CHES TORTILLERIA DIANA","149000001":"CHATT-EAST LA BONITA MEXICAN STORE","150000001":"RDU-EAST LA REGIA","152000001":"CLT-ROCK MEXICANA LA LAGUNA","153000001":"RDU-DUR SERVIAMERICA EXPRESS","154000001":"RDU-LOC ANA GOMEZ","155000001":"RDU-SOU LA CENTROAMERICANA GROSERY","156000001":"NASH - LOCAL VENUS SALON","157000001":"RDU-SOU EL MERCADO","158000001":"CLT-WEST LOS REYES MEXICAN STORE","159000001":"CLT-WEST EL TAMARINDO","160000001":"KNOX-NOR LA PLAZITA","162000001":"CHAR-LOC NELIDA MALDONADO","163000001":"CHATT-EAST TIENDA GENESIS","164000001":"CLT-LOC Gerardo Gomez","165000001":"RDU-SOU NINAS BOUTIQU","166000001":"WIL-LOC- LOS TRES HERMANOS","167000001":"WS-NOR LA GUADALUPANA","168000001":"WS-LOC LA TAPATIA","170000001":"KNOX-LOC HECTOR MANUEL SUT","171000001":"SC-LOCAL LUPITAS TIENDA LATINA","173000001":"COL - WEST TIENDA 3 CAMINOS","175000001":"CHAR-LOC TAQUERIA MOMENTOS MEXICA","176000001":"NASH - SOUTH 3S DIAMANETES","177000001":"RDU-EAST EL MANANTIAL","178000001":"WIL-NOR SUPER MERCADO LATINO","179000001":"CHAR-SAV 2 LOS ANGELES BEAUFORT","180000001":"CHATT-EAST TIENDA LA BENDICION MO","181000001":"CHATT-LOC TIENDA IXCOYENSE #2","182000001":"CLT-LOCAL TIENDA 504 HN","183000001":"CHAR-SAV 1 TIENDA MEXICANA VALLARTA","184000001":"CHATT-LOC TIENDA MARTINEZ","185000001":"CLT-ROCK LA YURIRENSE","186000001":"RDU-SOU LA PALMITA","188000001":"WIL-SOU LA MEJOR TIENDA LA CATRACHA","190000001":"CHATT-LOC TIENDA JUAREZ","192000001":"WIL-N WES TIENDA HISPANA LA FUERTE","193000001":"CHATT - WEST SUANI GARCIA","194000001":"COL - EAST TIENDA MEXICANA GUANAJUA","195000001":"RDU-LOC MI CASITA GROSERY STORE","196000001":"RDU-DUR MI VAQUITA","197000001":"JACK - NORTH EL PUERTO AZTECA","198000001":"RDU-DUR LA NUEVA MEXICANA","200000001":"NASH - NORTH MERCADITO LATINO","201000001":"CLT-LOC VARIEDADES VISION","202000001":"WIL-SOU LATINOS UNIDOS","203000001":"MAV-LOCAL EL MILAGRO RESTURANTA STO","204000001":"CHAR-LOC GUADALAJARA SUPER MARCKET","205000001":"CLT-LOC UNE CARGO EXPRESS","206000001":"SC-WEST 1 SUPERMERCADO CENTRAL","207000001":"SC-WEST 1 LA POBLANA","208000001":"COL - LOCAL MARIA GARCIA NEWBERRY","209000001":"WS-LOC ELEKTRA AMERICA","210000001":"SC-WEST 1 SANTO NIÑO RESTAURANT","211000001":"SC-LOCAL EL DIAMANTE","212000001":"CHAR-SAV 2 LA COMARCA GA","213000001":"JACK - NORTH RONAL MEDRA CANALES GA","215000001":"CLT-ROCK TIENDA HISPANA","219000001":"WS-NW JANNY'S SALON","220000001":"WS-WEST SUPER EL PAISA","222000001":"WS-LOC DON JUAN","223000001":"WS-WEST SUPER TIENDA MAYA","224000001":"RDU-LOC MARIA LANDA","225000001":"CLT-WEST ALEXA MINI MARKET","226000001":"WS-NOR LA COMERCIAL","228000001":"CHATT - WEST LA ESTRELLA","229000001":"WS-WEST EL TARASCO BANNER ELK","230000001":"CHAR-LOC TIENDA MEXICANA FRIDA","231000001":"RDU-DUR JORGE MANUEL ORTIZ","232000001":"WS-WEST MDL PARTY RENTALS (FIESTAS","235000001":"WS-VIRG TIENDA EL ROSARIO","236000001":"WIL-SOU TIENDA LAS AMERICAS 3","237000001":"WS-WEST TIENDA HICKORY COMPUTERS","238000001":"CHATT-LOC TIENDA SONTAY","239000001":"CHAR-SAV 2 LA FAVORITA GA","240000001":"SC-WEST 1 COSTA DE JALISCO","241000001":"CHAR-SAV 2 LA CONSENTIDA GA","243000001":"SC-EAST ROGELIOS MARKET","244000001":"NASH - SOUTH VARIEDADES GINA","245000001":"CHATT-LOC TIENDA LATINA 1","246000001":"CHATT-EAST VARIEDADES EL QUETZAL #4","247000001":"KNOX-NOR TIENDA MEXICANA EL MANANTI","248000001":"SC-LOCAL EL RANCHO GRANDE","251000001":"RDU-DUR EL CERRITO","252000001":"WIL-N WES TIENDA HISPANA EBEN-EZER","253000001":"WIL-SOU TIENDA EL TAMBOR","258000001":"CLT-LOC ESPERANZA","259000001":"SC-WEST 1 LA ESTRELLA","260000001":"RDU-EAST PEQUEÑO MEXICO LINDO","261000001":"CHATT-LOC PEACHY JUICE BAR","262000001":"COL - LOCAL LA VIOLETA MARKET MEXIC","265000001":"JACK - LOC PEPES HACIENDA","266000001":"Tu Caja Express Jacksonville","267000001":"CHAR-LOC GILBERTO RODRIGUEZ","268000001":"KNOX- WEST GUATEMEX","269000001":"WS-NOR LA PLAZITA MEXICAN GROSERY","270000001":"WIL-SOU LA OAXAQUENA","272000001":"JACK - LOC EL QUETZAL CUISINE CORP","273000001":"RDU-SOU TIENDA Y TORTILLERIA ROSITA","274000001":"WS-NW EL RANCHERO","276000001":"JACK - MAC LA GLORIA TIENDA Y TAQUE","277000001":"KNOX-LOC TIENDA LA CHIAPANECA","279000001":"WS-NOR MARCO GUZMAN","281000001":"NOVEDADES YEIMY GA-SC","282000001":"WS-LOC TIENDA SAN MIGUEL (LA TEJANA)","283000001":"CLT-LOC MAS POR MENOS","285000001":"COL - EAST LA BENDICION","286000001":"NASH - LOCAL ERNET ENVIOS","287000001":"RDU-DUR RINCON HISPANO MINI MART","289000001":"WS-LOC GLENN MART","290000001":"WIL-NOR JACKSONVILLE MARKET","291000001":"CHATT-EAST TIENDA VELASQUEZ","293000001":"WS-VIRG DOÑA MARIA","294000001":"COL - LOCAL DORIS SORIANO","295000001":"CLT-LOC SUPER TIENDA LATINA","296000001":"WS-LOC- RINCON LATINO","297000001":"RDU-EAST PLAZA SANTA ROSA","298000001":"CHAR-SAV 1 LA VERACRUZANA MILLEN","299000001":"KNOX- WEST CARNICERIA EL CAMINO","300000001":"CHAR-LOC LUVIO VELASQUEZ","301000001":"CHAR-LOC PANADERIA TLAXCALTITA","302000001":"CLT-LOCAL LA VIÑA MUEBLERIA Y MAS","303000001":"KNOX-LOC TIENDA CATRACHA","304000001":"WS-LOC ANNA'S GROCERYS","305000001":"CHATT - WEST MERCADOS PATTY","306000001":"WS-LOC TIENDA Y TAQUERIA MEX LA HUA","307000001":"NASH -NORTH EL TARASCO","308000001":"WIL-NOR LAS ESTRELLITAS","309000001":"CLT- LOC TIENDA NAVAS APPLIANCE","310000001":"CHATT-LOC TIENDA TODO SANTERITA","312000001":"CHAR-LOC LOS PUENTES DE JHON ISLAND","315000001":"COL - WEST TIENDA LA MEXICANA","316000001":"CHAR-LOC EL ALAZAN","317000001":"RDU-SOU PANADERIA EMMAS","318000001":"COL - WEST TIENDA HERNANDEZ","319000001":"SC-LOCAL EL FARAON","320000001":"RDU-SOU JM LATINOS SERVICES","321000001":"KNOX-LOC TIENDA EL GIRASOL","322000001":"VA-CHES TIENDA GUATEMALA LA BENDICI","323000001":"CHATT-LOC TIENDA Y FRUTERÍA TACANA","324000001":"CHATT - SOUTH TIENDA LA ESQUINITA","325000001":"NASH - LOCAL EL CAMINO MARKET","326000001":"KNOX-NOR TIENDA SAN JUANERITA","327000001":"WS-NW TIENDA DON JESUS","328000001":"WIL-SOU EL MERCADITO CHIAPANECO","330000001":"CLT-LOC MULTI ENVIOS CENTROAMERICA","332000001":"COL - LOCAL TIENDA LOS TRES POTRILL","333000001":"WS-NOR NOVEDADES MARIANGEL","334000001":"WS-NW TIENDA MEXICANA LOS POTRILLOS","335000001":"WS-WEST TAQUERIA EL TIO RICO","336000001":"Tu Caja Express WS","337000001":"KNOX-LOC LAS FUENTES","338000001":"KNOX-NOR TIENDA LA PRIMAVERA","339000001":"SC-LOCAL TIENDAS ALMART #3","340000001":"CHATT-LOC TIENDA EL EXITO","341000001":"RDU-EAST PANADERIA Y TIENDA EL DIAM","342000001":"WIL-N WES TIENDA Y TAQUERIA LA OAXA","343000001":"RDU-LOC ENVIOS EXPRESS (LA PASADITA","345000001":"CHAR-SAV 1 LA MORENITA JESUP GA","346000001":"WIL-NOR PANADERIA EL BUEN SAMARITAN","347000001":"NASH -NORTH HACIENDA LOS MIRANDA","349000001":"VA-CHES MI CASITA TIENDA LATINA","350000001":"WS-LOC LOS JUANES TIENDA LATINA","351000001":"VA-RICH A SELECTAS STORE","352000001":"WS-WEST AGUACATECO MORGANTON NC","353000001":"CLT-ROCK TIENDA MEXICANA EL LATINO","355000001":"CLT-WEST TIENDA LA CALENTANA","356000001":"CHAR-LOC SINE ART BAKERY LLC","357000001":"CLT-WEST LAS AMERICAS ROCK HILL","358000001":"CHAR-LOC HONDURAS GROSERY STORE","359000001":"KNOX-NOR LA PERLA #1","360000001":"COL - LOCAL TDA SUPER ACAPULCO","361000001":"COL - LOCAL VALVINA GALVEZ","362000001":"CLT-LOC TIENDA VIKIDS","363000001":"RDU-LOC LAS CAROLINAS","364000001":"WS-NOR FULL SERVICE","365000001":"WS-LOC NUTRICION LUZ","366000001":"WS-LOC TIENDA ACAPULCO","367000001":"RDU-DUR LA CHARRITA","369000001":"COL - WEST LA JALICENSE","370000001":"CHAR-SAV 2 TAQUERIA ROCIO RIDGLEAND","371000001":"CHAR-LOC LA MEXICANA 3","372000001":"CHATT-LOC SUPERMERCADO EL SOL","373000001":"COL - LOCAL MERCADO ACAPULCO","375000001":"RDU-SOU AZTECA MARKET","376000001":"WIL-SOU TIENDA MI GUATEMALA","377000001":"WS-VIRG TIENDA XPRESS 1","380000001":"NEIVIS COLLECTION GA","381000001":"SC-WEST 2 A ROSITA","382000001":"NASH - LOCAL BAKERY LA HISPANA","383000001":"JACK - LOC AMIGOS MARKET Y CANTINA","384000001":"CHATT - WEST TIENDA LA HACIENDA","385000001":"CHAR-SAV 1 LA MIXTECA","386000001":"WIL-SOU RINCONCITO SALVADORENO","387000001":"CHATT - SOUTH TIENDA EL SOL","388000001":"WIL-NOR EL MERCADITO","389000001":"CLT-LOC ESTETICA MEXICO MONROE","390000001":"CHAR-SAV 2 KENIA ROSA","391000001":"WIL-N WES EL CHAPEADO","393000001":"SC-EAST EL SOL GROCERY","395000001":"CLT-ROCK TIENDA MEXICO EL PARAISO","396000001":"COL - EAST JAZMIN LAKE CITY","397000001":"WIL-SOU TORTILLERIA HERMANOS","398000001":"WIL-SOU RESTAURANTE CHILE FRITO","399000001":"WS-NW MARTHA HERNANDEZ CLT","400000001":"RDU-DUR LA ESMERALDA TIENDA LATINA","401000001":"WIL-SOU CISSY'S TIENDA MEXICANA","402000001":"WIL-SOU MI MEXICO","403000001":"CLT-ROCK TIENDA MEXICANA JULIE ROCK","405000001":"CHAR-SAV 2 EL MANANTIAL","406000001":"CHAR-LOC LA GUADALUPANA","407000001":"COL - WEST LA GUADALAJARA","408000001":"COL - WEST LA GUADALAJARA AUGUSTA","409000001":"CHAR-SAV 1 SAN PEDRO STATESBORO GA","410000001":"WS-NOR HERMANOS CARBAJAL INC","411000001":"CHAR-SAV 1 TAQUERIA BIG JULIOS LYON","412000001":"CHAR-SAV 1 EL POBLANO ALMA GA","413000001":"JACK - NORTH LA JALISIENSE WAYCROSS","414000001":"CHAR-LOC GUADALAJARA SUPER MARKET 2","415000001":"CHAR-SAV 2 JESUS BEAUFORT","416000001":"CLT-LOC LAS MARAVILLAS CHARLOTTE","417000001":"KNOX- WEST TIENDA DE","418000001":"RDU-EAST TIENDA CASTAÑEDA","419000001":"CHATT-LOC FRANCISCA CRUZ","420000001":"WS-VIRG CLAUDIA FLORES","421000001":"KNOX- WEST MARGARITA RAMIREZ FERNAN","422000001":"KNOX- WEST LA CANASTA","424000001":"RDU-DUR VARIEDADES ROCIO 2","425000001":"KNOX- WEST TIENDA EL COCO LOKO","427000001":"RDU-EAST TIENDA HONDUMEX","428000001":"RDU-DUR MAXISERVICES LLC","429000001":"RDU-DUR MI TIERRA","430000001":"CLT-WEST LAS AMERICAS 3","431000001":"KNOX-NOR LA MEXICANA JOHNSON","432000001":"CHAR-LOC LA VENECIA","433000001":"RDU-LOC MI CASA GROCERY","434000001":"CHATT-LOC EL NORTEÑO BOOTS","435000001":"CLT-WEST TIENDA LATINA YORK","437000001":"CLT-WEST ORACIO SOLANO FLORES","438000001":"CHAR-SAV 2 CAROLINA FOOD INC","439000001":"CHAR-LOC LA FORTUNA","440000001":"JACK - MAC TIENDA LONCHERIA DONA LE","441000001":"WS-WEST ROSA ZAMORA LENOIR","442000001":"CHATT-LOC RITMO CALIENTE","443000001":"CLT- NORTH LA MEXICANA","444000001":"WS-NOR LA MILAGROSA","445000001":"VA-CHES JOSE Y MARIA DELI FOOD","446000001":"VA-RICH DELMY GARCIA","447000001":"JACK - SOUTH LA TIENDA DE MARIA FL","448000001":"RDU-EAST LA POTOSINA YANEZ INC","449000001":"WS-LOC LA TAPATIA 2 MT","450000001":"VA-CHES TIENDA MEXICANA LA DURANGUE","451000001":"JACK - LOC TIENDA LATINA MI GENTE","452000001":"WIL-NOR LAS CHICANITAS","454000001":"RDU-DUR TIENDA MOABITH","455000001":"WS-WEST LA TAPATIA 4","456000001":"RDU-EAST PEREZ STORE","457000001":"KNOX-LOC LA ESPERANZA","458000001":"NASH - NORTH DISCO TIENDA LATINA","459000001":"SC-WEST 2 LOS NENES BAKERY #2","460000001":"KNOX-LOC MI PUEBLO SUPER MERCADO","461000001":"WIL-N WES TIENDA LATINA EMMANUEL","462000001":"CHATT-LOC TIENDA SUPER GUATE","463000001":"WS-NW LUCKY FINNDS","464000001":"CHATT - SOUTH MEGA TIENDA 1","465000001":"WS-VIRG MSM WIRELESS","466000001":"RDU-EAST LA MEXICANA GROCERY","467000001":"WIL-NOR TIENDA LA MIXTECA INC","468000001":"WS-VIRG CARNICERIA EL MERCADITO EDE","469000001":"WS-LOC TIENDA EL MEXICANO","470000001":"SC-LOCAL LA FRESITA MEXICAN STORE","471000001":"WS-VIRG LOS KORITAS","472000001":"WIL-SOU TIENDA HISPANA MEXICO LINDO","473000001":"CHATT-LOC CHIHUAHUA'S TORTILLAS","474000001":"WS-VIRG RISE UP PROFESSIONAL SERVIC","475000001":"RDU-EAST INDIA BONITA","476000001":"RDU-SOU FRUTERIA LAS AMERICAS","477000001":"WS-WEST TIENDA ALTO LUCERO LLC","478000001":"KNOX- WEST MI LINDO CUERNAVACA","479000001":"RDU-SOU EL TIANGUIS","480000001":"WS-NOR 1 TOROS MEAT MARKET","481000001":"RDU-SOU LA ESTRELLA","482000001":"WIL-N WES EL RANCHO LATINOS IN","483000001":"CHATT - SOUTH TIPICOS MI GUATE","484000001":"WS-VIRG SUPER AMANECER 2","486000001":"CLT-WEST EDUARDO ZUNIGA","487000001":"WS-WEST VIVA SERVICESS","488000001":"JACK - LOC EL RINCONCITO SUPERMERCA","489000001":"Tu Caja Express VA","491000001":"WIL-SOU LA MICHOACANA","493000001":"WIL-LOC LEDI GONZALEZ CAMEY","494000001":"SC-WEST 2 CHAPALA GROCERIES 3","495000001":"SC-WEST 2 CHAPALA TIENDA #4","496000001":"SC-LOCAL EL TORITO GREER","498000001":"WIL-N WES TIENDA GUATEMALTECA LOPEZ","499000001":"KNOX-LOC TIENDA LA LUPITA #1","500000001":"KNOX-LOC TIENDA LA LUPITA #2","502000001":"VA-CHES Panificadora Lupitas","503000001":"CHAR-SAV 1 LAURAS MEXICAN STORE GA","504000001":"CLT-ROCK MEXICANA PAGELAND","505000001":"SC-WEST 2 MIRNA LOPEZ","506000001":"CHAR-LOC MI MEXICO LINDO 1","508000001":"KNOX-LOC LILAS MARKET","510000001":"CHATT-LOC ALVAREZ MARKET","511000001":"CHATT-LOC TIENDA LA PREFERIDA","512000001":"CHATT - CENTRO DE AYUDA CARTERSVILL","514000001":"CHATT-LOC LA GUATEMALTECA","515000001":"COL - EAST LOS TRES POTRILLOS","516000001":"RDU-SOU ARACELIS MEXICAN STORE","517000001":"CHATT - SOUTH TIENDA EBENEZER #2","518000001":"NASH - NORTH TIENDA LOS ANGELES","519000001":"SC-WEST 1 LA MEXICANITA INC","520000001":"CHATT-EAST TIENDA LOS PRIMOS","521000001":"SC-EAST MARINA RIOS","524000001":"TU CAJA EXPRESS HND","525000001":"WS-LOC UNIVERSAL TIENDA Y CARNICER","526000001":"CHATT-LOC WALFRE RAMIREZ","527000001":"CHATT-EAST LA HERRADURA TAQUERIA","528000001":"KNOX-LOC MI TIENDA","529000001":"KNOX-LOC BESSIE PEREZ","530000001":"CHAR-LOC LA SUPERIOR","531000001":"SC-EAST SUPER FAVORITA","532000001":"CLT-LOC MULTISERVICIOS HERNANDEZ","533000001":"WIL-N WES MEXICANA GARIBAY","534000001":"CHATT-LOC ANGELAS LIQUIDATION AND R","535000001":"RDU-LOC TIENDA CHECKS CASHED","536000001":"SC-LOCAL SUPERMERCADO EL MONTE","537000001":"CHATT - SOUTH EL SUPER QUETZAL ROME","538000001":"WS-WEST ELSA YOLANDA MORALES ENNICE","539000001":"JACK - MAC RICARDO LOPEZ","540000001":"WS-LOC MAXISERVICES LLC #2","541000001":"CHATT-LOC TIENDA SUPER GUATE","542000001":"KNOX-LOC LA RANCHERA MEXICAN MARKET","543000001":"SC-WEST 1 LATIN GIRLS SALON","544000001":"WS-NW LUCKYFINDS WHOLE SALE","545000001":"SC-EAST VIDA SERVICES LLC","546000001":"KNOX-NOR TIENDA LA MICHOACANA","547000001":"CLT-LOC TIENDA LA ADELITA","548000001":"CLT- LOC PRADERAS SUPER MARKET","549000001":"CHATT-LOC TIENDA MAYA","550000001":"CHATT-LOC AGENCIA EBENEZER","551000001":"NASH - NORTH EL BUEN CHAPIN","552000001":"VA-CHES RUTH PEREZ","553000001":"CHAR-SAV 1 TIENDA MEXICANA LUCERO K","554000001":"SC-LOCAL LA COSTENA","555000001":"NASH - NORTH TIENDA LA ETERNA PRIMA","556000001":"WS-NW PANADERIA Y TORTILLERIA LA IN","557000001":"KNOX-NOR LA ESPERANZA","558000001":"VA-CHES MINI MARKET SAN JOSE","560000001":"CHAR-SAV 2 TIENDA Y TORTILLERIA SAN","561000001":"CHAR-SAV 2 TAQUERIA EL GORDO","562000001":"NASH - NORTH TIENDA CHAPIN","563000001":"WIL-N WES LA ROCA MEXICAN STORE","564000001":"CHATT-LOC LA ESPERANZA","565000001":"SC-LOCAL TIENDA EL CUCHO","566000001":"NASH - SOUTH LUCERITO DOMINGUEZ","567000001":"WIL-NOR TIENDA LA CANASTA","569000001":"WS-NOR TIENDA MEXICANA TRES HERMANO","572000001":"CLT- NORTH R$C VARIETIES","573000001":"WIL-SOU SILVERIO PAXTOR","574000001":"WS-VIRG TIENDA XPRESS 2","575000001":"CHAR-SAV 1 SUCURSAL SALINAS LYONS G","576000001":"CLT-WEST LA BODEGA MULTISERVICES","577000001":"WS-NOR CARNICERIA EL KORA","578000001":"SC-WEST 2 MI GUSTO ES","579000001":"SC-WEST 2 CARNICERIA LA PREFERIDA","580000001":"KNOX-NOR LA COSTA CHICA","581000001":"RDU-DUR LA COSTENA","582000001":"RDU-EAST JOSE LUIS MEXICANITA","583000001":"CLT- LOC LA TIENDA MEXICANA","584000001":"CHATT-LOC TIENDA BUENABAJ","585000001":"KNOX-NOR LA PERLA #2","586000001":"WS-WEST TIENDA Y CARNICERIA MI NANC","587000001":"CLT-LOC TIENDA LA MEXICANITA","588000001":"CHATT-LOC LATIN STORE AND TACOS","589000001":"CHAR-LOC LA TAPATIA BAKERY","590000001":"CLT-WEST TIENDA MI PAIS LLS","591000001":"COL - LOCAL PANADERIA GUATELINDA","592000001":"CHAR-SAV 1 LA JOYA MARKET","593000001":"WS-LOC LINDO MICHOACAN TIENDA LLC","594000001":"CHATT - SOUTH CITY POSTAL CENTER","595000001":"CLT-LOC FRUTERIA EL BARRIO","596000001":"SC-WEST 2 LA ESPUELA DE ORO","597000001":"CLT- NORTH TIENDA RIOS DE AGUA VIVA","598000001":"WS-LOC LA VICTORIA 3 LLC","600000001":"CLT-LOC LAS AMERICAS SALON","601000001":"CHAR-LOC MIRNA GAMBOA","602000001":"CHATT-LOC SUPER LATINO","603000001":"SC-LOCAL PANADERIA LA BENDICION","604000001":"CHATT - WEST TIENDA LA VICTORIA 2","605000001":"TU CAJA EXPRESS CHATTANOOGA","606000001":"CHATT - SOUTH LA SONSONATECA INC","607000001":"CHATT - SOUTH ABARROTES MANUEL #1","612000001":"CHATT-LOC TIENDAS ALMART","615000001":"Tu Caja Express Nashville","616000001":"CHATT-LOC BRENDA LEON","619000001":"NASH -NORTH GUATEMEX SUPERMARKET","620000001":"CLT-LOC INTERCARGO","621000001":"WIL-N WES BRAVO SATELITE SERVICIOS","623000001":"CHAR-SAV 2 PEDRO CASTRO LOPEZ","627000001":"CHATT-LOC EL PARAISO","628000001":"JACK - MAC ODILIA PEREZ","630000001":"KNOX-LOC MARIA BERMUDEZ","631000001":"WS-NW LA TIENDA RINCON LATINO","632000001":"WIL-LOC TORTILLERIA EBENEZER Y LA T","637000001":"VA-RICH TAXES AMERICA","639000001":"KNOX-NOR NANA ANTOJITOS","640000001":"KNOX-LOC HECTOR MANUEL 2","642000001":"WIL-NOR SUPERMERCADO HISPANO INC","643000001":"WS-NOR RIO GRANDE MINI MARKET","644000001":"RDU-DUR TIENDA MI BARRIO","646000001":"RDU-SOU TIENDA AJ´S POIN LAUNBROAT","647000001":"SC-LOCAL TIENDA EL QUETZAL","649000001":"COL - EAST ROCK LA CORONA","652000001":"CHAR-SAV 2 PHONE GUYS","654000001":"JOJOS EXPRESS INC NJ","656000001":"RDU-SOU LA COSTA CHICA","660000001":"CHAR-SAV 2 PUPUSERIA JIREH","662000001":"CHATT-LOC TIENDA EBENEZER","663000001":"WS-WEST TIENDA EL PARAISO","664000001":"JACK - MAC UNY LATINO APPLIANCE Y S","666000001":"KNOX-LOC TIENDA LA BONITA","669000001":"WIL-SOUTH TIENDA LA PLAYA","671000001":"WS-WEST LAS 2 ROSAS CLT","673000001":"CHAR-LOC TIENDA LA FAMILIA","675000001":"WS-LOC HECTOR MENDOZA","676000001":"WS-VIRG SUPER LATINA ELIZABETH","677000001":"RDU-SOU TIENDA Y TORILLERIA LA FAVO","679000001":"VA-RICH EL NUEVO SABROSON","681000001":"CHAR-SAV 2 BLANCA ORDOÑEZ","684000001":"WS-NW NICAMAS SUPER MARKET","685000001":"WIL-LOC TIENDA LA ESMERALDA","686000001":"WS-WEST LA MONARCA TIENDA MEXICANA","687000001":"WIL-SOUTH TIENDA LATINA LA BENDICIO","691000001":"CHAR-SAV 2 UNCLE BENS MEAT MARKET","692000001":"CHATT - SOUTH EL SUPER QUETZAL DAL","693000001":"CLT-ROCK MEXICANA LA VICTORIA","694000001":"RDU-SOU SPEEDY GECKO SHIPPING","695000001":"NASH - LOCAL FERIAMEX","696000001":"CHATT - SOUTH TIENDA EL PARAISO","697000001":"COL - EAST YENIFER TAQUERIA","698000001":"CHAR-SAV 2 SUPER MERCADO EL DON JUA","699000001":"NASH - LOCAL BYS FACTORY EXPRESS","701000001":"SC-LOCAL TIENDA LA IDEAL","702000001":"NASH - SOUTH LOS AMIGOS SUPERMERCAD","703000001":"WIL-N WES MI TIENDITA SHANNON","704000001":"CHATT-EAST TIENDA MAYA","705000001":"CHAR-SAV 1 SEGURAS TAQUERIA Y TIEND","706000001":"CLT-ROCK TIENDA CARNICERIA Y TORTIL","707000001":"CHATT-EAST JUAN IGNACIO JUAN","708000001":"CLT- NORTH LA PALOMA","709000001":"SC-EAST SUPERMARKET LOS REYES","712000001":"SC-WEST 1 Veronica Franklin","713000001":"WIL-SOU ANGELICA CHAN DIAZ","715000001":"KNOX- WEST MERCADO DE ARTESANIAS CO","716000001":"WIL-N WES J & L GROCERY INC","718000001":"RDU-LOC TIENDA MULTIWHALES","719000001":"LA TAPATIA RDU","720000001":"JACK - MAC TRIUNFO MEXICAN STORE GA","721000001":"WIL-SOU TIENDA MEXICANA LA ROSITA","722000001":"RDU-DUR SAVERS LLC","723000001":"SC-LOCAL LA SUPERIOR TIENDA","724000001":"CHATT-EAST LOS REYES","726000001":"WIL-N WES TIENDA HISPANA 301 LA COC","727000001":"RDU-LOC ELIDA AQUINO","729000001":"NASH - SOUTH TRANSPORTES UNIDOS EXP","731000001":"CHATT-LOC TIENDA TIKAL","733000001":"WS-NW ISOLUTIONS USA","734000001":"RDU-DUR NUESTRO PORVENIR CORPORATIO","735000001":"RDU-DUR NOVEDADES Y TIENDA ROCIO","736000001":"CHATT-EAST LOS REYES SUPERMARKET","737000001":"WS-WEST EL CHARRITO","738000001":"COL - EAST TIENDA Y TAQUERIA CECILI","739000001":"NASH - LOCAL INDOOR SOCCER","740000001":"NASH - LOCAL EVA MERCADITO LATINO","742000001":"WIL-LOC MIREYA´S BOUTIQUE","744000001":"WS-NW TAQUERIA Y MARISQUERIA AZTLAN","746000001":"WIL-NOR TIENDA GOMEZ","747000001":"CLT-LOC PANADERIA EL QUETZAL MONROE","748000001":"WIL-NOR LA TIENDA LA SUPERIOR","749000001":"KNOX-NOR TIENDA LA FAMILIA MARIELA","750000001":"CHAR-LA GUADALUPANA SAVANNAH","755000001":"WS-WEST ZACULEU ABARROTERIA","756000001":"RDU-LOC EL SUPER INC","757000001":"CHATT-LOC MANUEL ANTONIO","758000001":"WS-WEST MARGARITAS CELL","759000001":"WS-NW TIENDA GUATEMALTECA LA SUPREM","760000001":"JACK - NORTH FRUITLAND Y MORE LLC","761000001":"WS-LOC EL PROGRESO","762000001":"CHATT-LOC VARIEDADES JASINTO","764000001":"NASH - NORTH RESTAURANTE EL PULGARC","766000001":"VA-CHES SARAY REYES","767000001":"CHATT - SOUTH TIENDA EBENEZER #1","768000001":"NASH - NORTH EL LATINO SUPERMARKET","769000001":"SC-LOCAL SUPER MERCADO EL TORITO","770000001":"CHATT-EAST TIENDA RAFAELENO","772000001":"SC-WEST 1 Mountainside Parcel & Pos","774000001":"JACK - MAC SUPER MERCADO EL PRIMO","775000001":"WS-WEST LOS TRES REYES","776000001":"JACK - MAC SUPER MERCADO Y CARNICER","780000001":"NASH - SOUTH MIGUEL AGUIRRE (COLECT","783000001":"WIL-N WES TIENDA LATINA 3 HERMANOS","785000001":"CHATT-LOC TIENDA EL CHARRITO","786000001":"CLT-WEST ELECKTRA GASTONIA","787000001":"CHAR-LOC MARIA VERA HERNANDEZ SC","788000001":"WS-LOC La Bendicion Market NC","789000001":"CHATT-LOC TIENDA LA ESTRELLA","790000001":"COL - LOCAL PELUQUERIA LATINA CECY","792000001":"CHATT - SOUTH VARIEDADES TÍPICAS MA","800000001":"CLT-ROCK TIENDA LA COSECHA","801000001":"WIL-LOC LA CHIQUITA #2","803000001":"TU CAJA EXPRESS GUATEMALA","806000001":"KNOX-NOR EL RANCHITO W.W.","808000001":"TU CAJA EXPRES 1","809000001":"RDU-DUR REGALITO DE ORO","811000001":"NASH - SOUTH MINI SUPER LOS 3 REYES","812000001":"WS-NOR CASA DE MARIA","813000001":"WS-NOR ISRAEL OCEA","816000001":"CHAR-SAV 2 LOS BUENOS DIAS","818000001":"NASH - NORTH TIENDA COATANECA","819000001":"CHATT-LOC TIENDA IXCOYENSE #1","821000001":"SC-WEST 2 La Popular Grocery Store","822000001":"Carga Express CLT","823000001":"KNOX-LOC WALTER SARSEÑO LÓPEZ TN","825000001":"CHATT-EAST TIENDA EL REY DAVID","826000001":"CHATT-EAST TIENDA LA ESPERANZA","827000001":"CHATT-LOC TIENDA LAS GEMELITAS","828000001":"NASH - SOUTH TIENDA CHAPIN","829000001":"CLT-LOC SERVICIOS LATINOS","830000001":"WIL-NOR SABORES LATINO","831000001":"COL - LOCAL TIENDA LA FE","833000001":"VA-RICH La Surianita LLC","834000001":"COL - WEST MARIA GARCIA NORTH AGUST","835000001":"KNOX-LOC YESSICA CARCAMO TN","836000001":"CHATT - SOUTH PANADERIA HIDALGUENSE","837000001":"RDU-DUR TIENDA LOS LAGO MEAT MARKET","838000001":"NASH - LOCAL MAZFRESCO MARKET","839000001":"CLT-LOC TIENDA LA GUATEMALTECA 2","840000001":"NASH - NORTH RESTAURANTE TACOS Y SA","841000001":"WIL-NOR TIENDA RAQUEL","842000001":"CHAR-SAV 2 OLIVIA CHINCHILLA GA","843000001":"CHAR-LOC MUNDO MEX","844000001":"SC-LOCAL EL PASO #7","846000001":"CHAR-LOC MI MEXICO LINDO 2","849000001":"CHATT-LOC TIENDA EMMANUEL","855000001":"WS-VIRG LOS NAYARITAS","857000001":"CLT-LOC ELECKTRA #2","858000001":"CHATT-LOC MISS G'S TORTAS","859000001":"SC-LOCAL EL PASO #3","860000001":"SC-WEST 1 MUNDO HISPANO","862000001":"CHAR-LOC TIENDA Y PANADERIA MI MEXI","865000001":"Tu Caja Express Knoxville","866000001":"CHAR-LOC MARIO GUTIRREZ VELASQUEZ","872000001":"WS-NW ENVIOS DE CAJAS Y MUDANZAS LL","873000001":"CHATT - SOUTH ERENIA WILSON","874000001":"CLT- NORTH EL EXITO EXPRESS","875000001":"WS-NOR LOS PAISAS","876000001":"Next Day Cargo FL","877000001":"RDU-SOU PANADERIA Y PASTELERIA EL S","879000001":"CHATT - WEST LA VERACRUZANA","880000001":"WS-NOR LAS POBLANITAS","882000001":"KNOX-LOC EL PRIMO PRODUCTS HISPANOS","883000001":"RDU-DUR LA VERACRUZANA","884000001":"RDU-EAST EL CHARRITO DEL MANTE","885000001":"WS-NOR TIENDA HISPANA TU CASA","886000001":"KNOX-LOC ESTHER DALILA ZATETA","887000001":"COL - LOCAL EL MEXICANO","888000001":"CLT- NORTH TIENDA LATINA LA CHIQUIT","889000001":"WS-WEST TIENDA DON CHUY","890000001":"NASH - SOUTH EL MILAGRO CARGO EXPRE","891000001":"WS-WEST LA COMERCIAL","892000001":"CLT-LOC TIENDA LOS PICHONES","893000001":"CHATT-LOC TIENDA GARCIA","894000001":"SC-WEST 1 ISHYS GRILL","895000001":"WS-LOC PALMA FURNITURE","897000001":"SC-WEST 2 Scramble Cafe NC","899000001":"WIL-SOU MEXICAN STORE LA PASADITA","900000001":"CLT-LOC EL RINCON","901000001":"WS-WEST TIENDA LA ESMELADA","902000001":"RDU-DUR MOROLEON SUPERMARKET","903000001":"CLT-WEST MEDIA LUNA MINI MARK","904000001":"WS-WEST BIOTU TERRA","906000001":"CHATT-EAST TIENDA EL QUETZAL","907000001":"VA-CHES CASA HISPANA","908000001":"RDU-SOU LA PRIMAVERA","910000001":"WIL-NOR TIENDA YULI","912000001":"WS-WEST SOOTHILLS UNIVERSAL SERVICE","913000001":"Tu Caja Express Proveedores CA","914000001":"TU CAJA EXPRESS GTM","915000001":"CHATT-EAST TIENDA EBENEZER FORT PAY","916000001":"KNOX-NOR TIENDA Y CARNICERIA LA ESP","917000001":"KNOX- WEST TIENDA LA CHIQUITITA","918000001":"RDU-SOU TIENDA MI QUINCEAÑERA","919000001":"VA-CHES GRANDY ONE STOP","920000001":"TU CAJA TRANSFERENCIAS Y REMESAS","922000001":"WS-WEST TAQUERIA EL TROMPO","923000001":"TU CAJA CHICA CHARLOTTE","924000001":"TU CAJA CHICA RALEIGH","925000001":"CHATT-LOC BYRON SONTAY","926000001":"WS-NOR 2 TOROS MEAT MARKET","927000001":"WS-NW TIENDA LA SURTIDITA","928000001":"WS-NOR TIENDA EL EXITO","929000001":"WS-LOC FLORERIA HORTENSIA'S","930000001":"WS-NOR ENVIOS EL OLANCHANO","931000001":"WS-NOR PANADERIA Y TORTILLERIA RAMI","932000001":"CLT-LOC ELEVATED NUTRICION","933000001":"CLT-WEST TIENDA LATINA LLC","934000001":"WIL-LOC EL PASO TIENDA LATINA","935000001":"TU CAJA CHICA 3 CLT","936000001":"VA-RICH 2 SISTERS MARKET INC","937000001":"RDU-SOU GLAMOUR","938000001":"RDU-EAST TIENDA EL CAMPESINO","939000001":"CLT-ROCK BARCO PRODUCE","940000001":"WS-NOR LATINO 7 MARK","941000001":"KNOX-LOC LA PEQUEÑITA","942000001":"WS-NW ESQUINA LATINA MINI MARKET","943000001":"WIL-N WES NIDIA GUTIERREZ","944000001":"WS-VIRG CARNICERIA 2 TOROS MEAT MAR","945000001":"KNOX-LOC MONARCA TIENDA Y CARNICERI","946000001":"COL - EAST MINI MARKET LARIOS","947000001":"KNOX-LOC ESTEBAN BALTAZAR","948000001":"NASH - LOCAL MELVIN VALDEZ","949000001":"WIL-NOR TIENDITA SOLIS","950000001":"RDU-SOU TIENDA CASH","951000001":"WIL-SOU GUANAJUATO MEXICAN STORE","952000001":"WIL-SOU VIA MEXICO","954000001":"CHAR-LOC Tienda Mexicana La Azteca","955000001":"WS-NW SILER AUTOMOTIVE NC","956000001":"WS-LOC 2 HERMANOS TIENDA MEX","957000001":"SC-WEST 1 WHITE HOUSE GENERAL STORE","958000001":"RDU-DUR EL SUPER INC #2","959000001":"NASH - NORTH LA MARQUENSITA","960000001":"WIL-SOU TIENDA HONDUREÑA LA ECONOMI","961000001":"CLT-LOC LA GUADALUPANA TIENDA LATIN","962000001":"WIL-N WES TIENDA Y CARNICERIA LA TA","963000001":"CHATT - WEST SUPERMERCADO COLONIAL","964000001":"WS-WEST ALIVAS MULTISERVICES LLC","965000001":"KNOX-NOR EXPRESS LATINO EL CHAPIN","966000001":"Tu Caja Transitos","967000001":"CLT-LOC TIENDA UNIÓN SOCCER ARENA","968000001":"CLT-WEST TIENDA MONDRAGON MEXICAN S","969000001":"CHATT-EAST LA GUADALUPE","970000001":"TU CAJA GASTOS OPERATIVOS USA","971000001":"TU CAJA GASTOS OPERATIVOS GTM","972000001":"TU CAJA GASTOS OPERATIVOS HND","974000001":"NASH - NORTH RAZA LATINA","975000001":"KNOX-NOR TIENDA IXTATECO #2","977000001":"TU CAJA TRANSITOS GTM","978000001":"NASH - SOUTH SAN MARCOS SUPERMERCAD","979000001":"CHAR-SAV 2 MIRNA MARIA LUISA FOLGAR","980000001":"CLT-WEST TIENDA LA PROVINCIA","981000001":"RDU-DUR DINORA ACEITUNO","982000001":"JACK - NORTH LA JALISIENSE II","983000001":"NASH - SOUTH EL GALLITO #2","984000001":"NASH - LOCAL EL GALLITO #1","985000001":"KNOX-NOR TIENDA LATINA LA CHIQUITA","986000001":"CLT-LOC ABARROTES SOL DEL VALLE","987000001":"JACK - MAC RANCHO MHEXENI & GRILL","988000001":"SC-EAST TIENDA LA ESPERANZA MACO","989000001":"JACK - MAC HISPANO AMERICAN #1 WAR","990000001":"JACK - MAC HISPANO AMERICAN #2","991000001":"NASH - LOCAL NORTH SUPER FIESTA LAT","992000001":"CHATT-EAST TIENDA EBENEZER BESSEMER","993000001":"KNOX- WEST LA TIENDA GUATEMALA LLC","994000001":"KNOX- WEST IMPERIO MULTISERVICES LL","995000001":"JACK - MAC LA PIÑA LOCA","996000001":"SC-LOCAL MEXICO LINDO","997000001":"RDU-EAST LA POTOSINA TACO EXPRESS","998000001":"CLT-LOC MARIBEL SAUCEDO VELASQUEZ","999000001":"KNOX-NOR MI TIERRA MARKET","1001000001":"CHATT-LOC TIENDA GUATEMEX","1002000001":"CHATT - WEST TULLAHOMA SUPERMERCADO","1003000001":"WS-NOR LA PROVIDENCIA","1004000001":"JACK - MAC MI CASA COLUMBUS","1005000001":"CHATT-LOC LA TIENDITA","1006000001":"KNOX- WEST TIENDA MEXICANA LA JAROC","1007000001":"KNOX- WEST MULTI-SERVICIOS LATINOS","1008000001":"KNOX-NOR-TIENDA LA ESQUINA","1009000001":"SC-WEST- CAPA SURI","1010000001":"SC-EAST JESSY´S MARKET","1011000001":"JACK - MAC TIENDA SAN MARCOS","1012000001":"CHATT-EAST TIENDA EBENEZER ALBERTVI","1013000001":"KNOX- WEST TIENDA Y PANADERIA LA BE","1014000001":"KNOX- WEST TIENDA LA MORENITA MEAT","1016000001":"Remesas GTM","1021000001":"Tu Caja Express Sociedad Anonima","CODIGO":"AGENCIA"}]